README.md
setup.py
AIMakerMonitor/VERSION
AIMakerMonitor/__init__.py
AIMakerMonitor/prometheus.py
AIMakerMonitor.egg-info/PKG-INFO
AIMakerMonitor.egg-info/SOURCES.txt
AIMakerMonitor.egg-info/dependency_links.txt
AIMakerMonitor.egg-info/not-zip-safe
AIMakerMonitor.egg-info/requires.txt
AIMakerMonitor.egg-info/top_level.txt