Metadata-Version: 1.0
Name: AIMakerMonitor
Version: 1.0.5
Summary: monitor the result from inference server
Home-page: UNKNOWN
Author: scott_su
Author-email: scott_su@asus.com
License: MIT
Platform: UNKNOWN
